lib1305/__init__.py
lib1305/_lib.py
lib1305/onetimeauth.py
lib1305-20250415.1.dist-info/licenses/LICENSE
lib1305-20250415.1.dist-info/METADATA
lib1305-20250415.1.dist-info/WHEEL
lib1305-20250415.1.dist-info/top_level.txt
lib1305-20250415.1.dist-info/RECORD
