Metadata-Version: 2.4
Name: lib1305
Version: 20250415.1
Summary: Python wrapper around implementation of the Poly1305 one-time authenticator
Author-email: Jan Mojžíš <jan.mojzis@gmail.com>
License: Creative Commons Legal Code
Requires-Python: >=3.7
License-File: LICENSE
Dynamic: license-file
